{"restaurant": {"deeplink": "zomato://restaurant/1701384", "id": "1701384", "name": "Biku", "price_range": 3, "offers": [], "user_rating": {"aggregate_rating": "4.3", "votes": "226", "rating_text": "Very Good", "rating_color": "5BA829"}, "featured_image": "https://b.zmtcdn.com/data/pictures/4/1701384/8a42d6ba0e250d2449699a46a97898bf_featured_v2.jpg", "has_online_delivery": 0, "cuisines": "Western", "is_delivering_now": 0, "location": {"locality": "Seminyak", "zipcode": "", "country_id": 94, "city_id": 170, "longitude": "115.1538250000", "locality_verbose": "Seminyak, Bali", "latitude": "-8.6784027778", "address": "Jl. Petitenget, Seminyak, Bali", "city": "Bali", "country_name": "Indonesia"}, "establishment_types": [], "photos_url": "https://www.zomato.com/bali/biku-seminyak/photos?utm_source=api_basic_user&utm_medium=api&utm_campaign=v2.1#tabtop", "switch_to_order_menu": 0, "average_cost_for_two": 300000, "events_url": "https://www.zomato.com/bali/biku-seminyak/events#tabtop?utm_source=api_basic_user&utm_medium=api&utm_campaign=v2.1", "currency": "IDR", "apikey": "3945ef0104d65c9aaaf7611037e81618", "thumb": "https://b.zmtcdn.com/data/pictures/4/1701384/8a42d6ba0e250d2449699a46a97898bf_featured_v2.jpg", "url": "https://www.zomato.com/bali/biku-seminyak?utm_source=api_basic_user&utm_medium=api&utm_campaign=v2.1", "menu_url": "https://www.zomato.com/bali/biku-seminyak/menu?utm_source=api_basic_user&utm_medium=api&utm_campaign=v2.1&openSwipeBox=menu&showMinimal=1#tabtop", "R": {"res_id": 1701384}, "has_table_booking": 0}}