{"restaurant": {"events_url": "https://www.zomato.com/ottawa/atelier-ottawa/events#tabtop?utm_source=api_basic_user&utm_medium=api&utm_campaign=v2.1", "apikey": "3945ef0104d65c9aaaf7611037e81618", "establishment_types": [], "price_range": 4, "cuisines": "Canadian", "average_cost_for_two": 250, "deeplink": "zomato://restaurant/16663397", "user_rating": {"rating_text": "Very Good", "aggregate_rating": "4.0", "rating_color": "5BA829", "votes": "487"}, "photos_url": "https://www.zomato.com/ottawa/atelier-ottawa/photos?utm_source=api_basic_user&utm_medium=api&utm_campaign=v2.1#tabtop", "thumb": "https://b.zmtcdn.com/data/pictures/7/16663397/e5edfc4c2ebb2779c29129a00e6b6328_featured_v2.jpg", "id": "16663397", "currency": "$", "has_table_booking": 0, "location": {"city_id": 295, "locality_verbose": "Little Italy, Ottawa", "locality": "Little Italy", "city": "Ottawa", "longitude": "-75.7064050000", "address": "540 Rochester Street, Ottawa, ON K1A 0E4", "country_id": 37, "latitude": "45.3995580000", "country_name": "Canada", "zipcode": "K1A 0E4"}, "is_delivering_now": 0, "offers": [], "menu_url": "https://www.zomato.com/ottawa/atelier-ottawa/menu?utm_source=api_basic_user&utm_medium=api&utm_campaign=v2.1&openSwipeBox=menu&showMinimal=1#tabtop", "switch_to_order_menu": 0, "url": "https://www.zomato.com/ottawa/atelier-ottawa?utm_source=api_basic_user&utm_medium=api&utm_campaign=v2.1", "R": {"res_id": 16663397}, "has_online_delivery": 0, "name": "Atelier", "featured_image": "https://b.zmtcdn.com/data/pictures/7/16663397/e5edfc4c2ebb2779c29129a00e6b6328_featured_v2.jpg"}}