{"restaurant": {"events_url": "https://www.zomato.com/rzeszów/saigon-rzeszów/events#tabtop?utm_source=api_basic_user&utm_medium=api&utm_campaign=v2.1", "apikey": "3945ef0104d65c9aaaf7611037e81618", "establishment_types": [], "price_range": 1, "cuisines": "Chinese, Vietnamese", "average_cost_for_two": 35, "deeplink": "zomato://restaurant/16533997", "user_rating": {"rating_text": "Average", "aggregate_rating": "3.2", "rating_color": "CDD614", "votes": "11"}, "photos_url": "https://www.zomato.com/rzeszów/saigon-rzeszów/photos?utm_source=api_basic_user&utm_medium=api&utm_campaign=v2.1#tabtop", "thumb": "", "id": "16533997", "currency": "zł", "has_table_booking": 0, "location": {"city_id": 267, "locality_verbose": "Rzeszów, Rzeszów", "locality": "Rzeszów", "city": "Rzeszów", "longitude": "22.0069510000", "address": "Jana III Sobieskiego 14, Rzeszów, Rzeszów", "country_id": 163, "latitude": "50.0392370000", "country_name": "Poland", "zipcode": ""}, "is_delivering_now": 0, "offers": [], "menu_url": "https://www.zomato.com/rzeszów/saigon-rzeszów/menu?utm_source=api_basic_user&utm_medium=api&utm_campaign=v2.1&openSwipeBox=menu&showMinimal=1#tabtop", "switch_to_order_menu": 0, "url": "https://www.zomato.com/rzeszów/saigon-rzeszów?utm_source=api_basic_user&utm_medium=api&utm_campaign=v2.1", "R": {"res_id": 16533997}, "has_online_delivery": 0, "name": "Saigon", "featured_image": ""}}