{"restaurant": {"R": {"res_id": 17452111}, "events_url": "https://www.zomato.com/lima-oh/bangkok-bay-lima/events#tabtop?utm_source=api_basic_user&utm_medium=api&utm_campaign=v2.1", "switch_to_order_menu": 0, "user_rating": {"votes": "69", "rating_text": "Very Good", "aggregate_rating": "4.0", "rating_color": "5BA829"}, "average_cost_for_two": 10, "photos_url": "https://www.zomato.com/lima-oh/bangkok-bay-lima/photos?utm_source=api_basic_user&utm_medium=api&utm_campaign=v2.1#tabtop", "has_online_delivery": 0, "deeplink": "zomato://restaurant/17452111", "apikey": "2ce803cdd97585066baf42ed16933114", "is_delivering_now": 0, "establishment_types": [], "offers": [], "location": {"zipcode": "45804", "locality": "Lima", "country_name": "United States", "countryName": "United States", "locality_verbose": "Lima, Lima", "latitude": "40.6928110000", "longitude": "-84.1259200000", "country_id": 216, "city": "Lima", "address": "3280 S Dixie Hwy, Lima, OH 45804", "city_id": 1039}, "cuisines": "Thai", "price_range": 1, "featured_image": "https://b.zmtcdn.com/data/pictures/1/17452111/69e3c07021b4598eff570196a8e93536_featured_v2.jpg", "menu_url": "https://www.zomato.com/lima-oh/bangkok-bay-lima/menu?utm_source=api_basic_user&utm_medium=api&utm_campaign=v2.1&openSwipeBox=menu&showMinimal=1#tabtop", "has_table_booking": 0, "id": "17452111", "name": "Bangkok Bay", "url": "https://www.zomato.com/lima-oh/bangkok-bay-lima?utm_source=api_basic_user&utm_medium=api&utm_campaign=v2.1", "thumb": "https://b.zmtcdn.com/data/pictures/1/17452111/69e3c07021b4598eff570196a8e93536_featured_v2.jpg", "currency": "$"}}