{"restaurant": {"events_url": "https://www.zomato.com/banff-ab/cows-banff/events#tabtop?utm_source=api_basic_user&utm_medium=api&utm_campaign=v2.1", "apikey": "3945ef0104d65c9aaaf7611037e81618", "establishment_types": [], "price_range": 1, "cuisines": "Desserts", "average_cost_for_two": 10, "deeplink": "zomato://restaurant/16641822", "user_rating": {"rating_text": "Good", "aggregate_rating": "3.8", "rating_color": "9ACD32", "votes": "133"}, "photos_url": "https://www.zomato.com/banff-ab/cows-banff/photos?utm_source=api_basic_user&utm_medium=api&utm_campaign=v2.1#tabtop", "thumb": "", "id": "16641822", "currency": "$", "has_table_booking": 0, "location": {"city_id": 2866, "locality_verbose": "Banff, Banff", "locality": "Banff", "city": "Banff", "longitude": "-115.5707260000", "address": "134 Banff Ave., Banff, AB T1L", "country_id": 37, "latitude": "51.1751560000", "country_name": "Canada", "zipcode": "T1L"}, "is_delivering_now": 0, "offers": [], "menu_url": "https://www.zomato.com/banff-ab/cows-banff/menu?utm_source=api_basic_user&utm_medium=api&utm_campaign=v2.1&openSwipeBox=menu&showMinimal=1#tabtop", "switch_to_order_menu": 0, "url": "https://www.zomato.com/banff-ab/cows-banff?utm_source=api_basic_user&utm_medium=api&utm_campaign=v2.1", "R": {"res_id": 16641822}, "has_online_delivery": 0, "name": "Cows", "featured_image": ""}}