{"restaurant": {"events_url": "https://www.zomato.com/nagpur/veeraswami-sadar/events#tabtop?utm_source=api_basic_user&utm_medium=api&utm_campaign=v2.1", "apikey": "3945ef0104d65c9aaaf7611037e81618", "establishment_types": [], "price_range": 1, "cuisines": "South Indian", "average_cost_for_two": 250, "deeplink": "zomato://restaurant/3300060", "user_rating": {"rating_text": "Very Good", "aggregate_rating": "4.3", "rating_color": "5BA829", "votes": "196"}, "photos_url": "https://www.zomato.com/nagpur/veeraswami-sadar/photos?utm_source=api_basic_user&utm_medium=api&utm_campaign=v2.1#tabtop", "thumb": "https://b.zmtcdn.com/data/pictures/0/3300060/792355f13d92266262ab67cb81596658_featured_v2.jpg", "id": "3300060", "currency": "Rs.", "has_table_booking": 0, "location": {"city_id": 33, "locality_verbose": "Sadar, Nagpur", "locality": "Sadar", "city": "Nagpur", "longitude": "79.0797256306", "address": "LIC Building, Link Road, Mount Road Extension, S.Bazar, Sadar, Nagpur", "country_id": 1, "latitude": "21.1588848527", "country_name": "India", "zipcode": ""}, "is_delivering_now": 0, "offers": [], "menu_url": "https://www.zomato.com/nagpur/veeraswami-sadar/menu?utm_source=api_basic_user&utm_medium=api&utm_campaign=v2.1&openSwipeBox=menu&showMinimal=1#tabtop", "switch_to_order_menu": 0, "url": "https://www.zomato.com/nagpur/veeraswami-sadar?utm_source=api_basic_user&utm_medium=api&utm_campaign=v2.1", "R": {"res_id": 3300060}, "has_online_delivery": 1, "name": "Veeraswami", "featured_image": "https://b.zmtcdn.com/data/pictures/0/3300060/792355f13d92266262ab67cb81596658_featured_v2.jpg"}}